bootstrap_ui/__init__.py
bootstrap_ui/templates/bootstrap_ui/bootstrap3-skeleton.html
bootstrap_ui/templates/bootstrap_ui/bootstrap4-skeleton.html
bootstrap_ui/templates/bootstrap_ui/bootstrap5-skeleton.html
bootstrap_ui/templates/bootstrap_ui/html5-skeleton.html
django_bootstrap_ui-4.0.0.dist-info/LICENSE
django_bootstrap_ui-4.0.0.dist-info/METADATA
django_bootstrap_ui-4.0.0.dist-info/WHEEL
django_bootstrap_ui-4.0.0.dist-info/top_level.txt
django_bootstrap_ui-4.0.0.dist-info/RECORD
