Metadata-Version: 2.1
Name: django-bootstrap-ui
Version: 4.0.0
Summary: django-bootstrap-ui simplifies the integration of the popular Bootstrap UI framework
Home-page: https://gitlab.com/texperience/django-bootstrap-ui
Author: Timo Rieber
Author-email: trieber@texperience.de
License: ISC License (ISCL)
Classifier: Development Status :: 5 - Production/Stable
Classifier: Environment :: Web Environment
Classifier: Framework :: Django
Classifier: Framework :: Django :: 4.2
Classifier: Framework :: Django :: 5.0
Classifier: Framework :: Django :: 5.1
Classifier: Framework :: Django :: 5.2
Classifier: Intended Audience :: Developers
Classifier: License :: OSI Approved :: ISC License (ISCL)
Classifier: Operating System :: OS Independent
Classifier: Programming Language :: Python
Classifier: Programming Language :: Python :: 3
Classifier: Programming Language :: Python :: 3.8
Classifier: Programming Language :: Python :: 3.9
Classifier: Programming Language :: Python :: 3.10
Classifier: Programming Language :: Python :: 3.11
Classifier: Programming Language :: Python :: 3.12
Classifier: Programming Language :: Python :: 3.13
Classifier: Topic :: Internet :: WWW/HTTP
Classifier: Topic :: Internet :: WWW/HTTP :: Dynamic Content
License-File: LICENSE
Requires-Dist: django<5.3,>=4.2
Provides-Extra: building
Requires-Dist: mkdocs-material<10.0,>=9.4; extra == "building"
Provides-Extra: development
Requires-Dist: mkdocs-material<10.0,>=9.4; extra == "development"
Requires-Dist: flake8<7.0,>=6.0; extra == "development"
Requires-Dist: tox<4.0,>=3.28; extra == "development"
Provides-Extra: linting
Requires-Dist: flake8<7.0,>=6.0; extra == "linting"
Provides-Extra: testing
Requires-Dist: tox<4.0,>=3.28; extra == "testing"
